sphinx_csv_filter-0.4.2-py3.12-nspkg.pth
crate/sphinx/__init__.py
crate/sphinx/csv.py
sphinx_csv_filter-0.4.2.dist-info/LICENSE
sphinx_csv_filter-0.4.2.dist-info/METADATA
sphinx_csv_filter-0.4.2.dist-info/WHEEL
sphinx_csv_filter-0.4.2.dist-info/namespace_packages.txt
sphinx_csv_filter-0.4.2.dist-info/top_level.txt
sphinx_csv_filter-0.4.2.dist-info/RECORD
