Metadata-Version: 2.1
Name: sphinx-csv-filter
Version: 0.4.2
Summary: A CSV filter directive for docutils and Sphinx, that extends the "csv-table" reStructuredText directive to add row filtering options.
Home-page: https://github.com/crate/sphinx_csv_filter
Author: Crate.IO GmbH
Author-email: office@crate.io
License: Apache License 2.0
Keywords: sphinx csv filter docutils directive plugin csv-table csv-filter restructuredtext
Platform: any
Classifier: Development Status :: 4 - Beta
Classifier: Intended Audience :: Developers
Classifier: License :: OSI Approved :: Apache Software License
Classifier: Operating System :: OS Independent
Classifier: Programming Language :: Python
Classifier: Programming Language :: Python :: 3
Classifier: Programming Language :: Python :: 3.8
Classifier: Programming Language :: Python :: 3.9
Classifier: Programming Language :: Python :: 3.10
Classifier: Programming Language :: Python :: 3.11
Classifier: Programming Language :: Python :: 3.12
Classifier: Programming Language :: Python :: 3.13
Classifier: Programming Language :: Python :: Implementation :: CPython
Classifier: Topic :: Documentation
Classifier: Topic :: Documentation :: Sphinx
Classifier: Topic :: Education
Classifier: Topic :: Software Development :: Code Generators
Classifier: Topic :: Software Development :: Documentation
Classifier: Topic :: Text Processing :: Markup :: reStructuredText
Requires-Python: >=3.3
License-File: LICENSE
Requires-Dist: Sphinx
Provides-Extra: development
Requires-Dist: build ; extra == 'development'
Requires-Dist: setuptools ; extra == 'development'
Requires-Dist: twine ; extra == 'development'
Requires-Dist: wheel ; extra == 'development'
Provides-Extra: testing
Requires-Dist: flake8 ; extra == 'testing'
Requires-Dist: pytest ; extra == 'testing'
Requires-Dist: pytest-cov ; extra == 'testing'
Requires-Dist: pytest-flake8 ; extra == 'testing'
Requires-Dist: pytest-isort ; extra == 'testing'
